integrao/IntegrAO_supervised.py
integrao/IntegrAO_unsupervised.py
integrao/__init__.py
integrao/dataset.py
integrao/integrater.py
integrao/main.py
integrao/supervised_train.py
integrao/unsupervised_train.py
integrao/util.py
integrao-0.1.3.dist-info/METADATA
integrao-0.1.3.dist-info/WHEEL
integrao-0.1.3.dist-info/licenses/LICENSE
integrao-0.1.3.dist-info/RECORD
