Metadata-Version: 2.4
Name: integrao
Version: 0.1.3
Summary: The Python implementation of the IntegrAO.
Project-URL: Homepage, https://github.com/bowang-lab/IntegrAO
Project-URL: Issues, https://github.com/bowang-lab/IntegrAO/issues
Author-email: Shihao Ma <rex.ma@mail.utoronto.ca>
License-File: LICENSE
Classifier: License :: OSI Approved :: MIT License
Classifier: Operating System :: OS Independent
Classifier: Programming Language :: Python :: 3
Requires-Python: >=3.9
Requires-Dist: networkx==3.0
Requires-Dist: numpy>=1.24.1
Requires-Dist: pandas>=1.3.5
Requires-Dist: scikit-learn==1.3.2
Requires-Dist: scipy==1.11.4
Requires-Dist: snfpy
Requires-Dist: torch-geometric>=2.3.0
Requires-Dist: umap-learn>=0.5.5
